<?xml version="1.0" encoding="utf-8"?>
<root>
	<testRadio>
		<item>
			<dlgStyle> checkbox </dlgStyle>
			<name> 测试1 </name>
			<value> 0 </value>
			<checked> 1 </checked>
		</item>
		<item>
			<dlgStyle> checkbox </dlgStyle>
			<name> 测试2 </name>
			<value> 1 </value>
		</item>
		<item>
			<dlgStyle> checkbox </dlgStyle>
			<name> 测试3 </name>
			<value> 2 </value>
			<param>
				<dlgStyle> combobox
					<item>
						<name> 高攀1 </name>
						<value> 0 </value>
					</item>
					<item>
						<name> 高攀2 </name>
						<value> 1 </value>
					</item>
					<item>
						<name> 高攀3 </name>
						<value> 2 </value>
					</item>
				</dlgStyle>
				<name> 参数1 </name>
				<cname> param1 </cname>
				<reverse> bool </reverse>
				<default> 高攀1 </default>
				<descr> 参数注释1 </descr>
				<width> 50 </width>
			</param>
			<param>
				<dlgStyle> comcheckbox
					<item>
						<name> gp1 </name>
						<value> 0 </value>
					</item>
					<item>
						<name> gp2 </name>
						<value> 1 </value>
					</item>
					<item>
						<name> gp3 </name>
						<value> 2 </value>
					</item>
				</dlgStyle>
				<name> 参数2 </name>
				<cname> param2 </cname>
				<reverse> bool </reverse>
				<default> gp1 </default>
				<descr> 参数注释2 </descr>
				<width> 50 </width>
			</param>
		</item>
	</testRadio>
	
	<testCheck>
		<item>
			<dlgStyle> radio </dlgStyle>
			<name> 测试1 </name>
			<value> 0 </value>
			<checked> 1 </checked>
			<nonewline> 1 </nonewline>
			<descr> 注释 </descr>
			<param>
				<dlgStyle> combobox
					<item>
						<name> 高攀1 </name>
						<value> 0 </value>
					</item>
					<item>
						<name> 高攀2 </name>
						<value> 1 </value>
					</item>
					<item>
						<name> 高攀3 </name>
						<value> 2 </value>
					</item>
					<item>
						<name> 高攀4 </name>
						<value> 3 </value>
					</item>
					<item>
						<name> 高攀5 </name>
						<value> 4 </value>
					</item>
					<item>
						<name> 高攀6 </name>
						<value> 5 </value>
					</item>
					<item>
						<name> 高攀7 </name>
						<value> 6 </value>
					</item>
					<item>
						<name> 高攀8 </name>
						<value> 7 </value>
					</item>
					<item>
						<name> 高攀9 </name>
						<value> 8 </value>
					</item>
				</dlgStyle>
				<name> 参数1 </name>
				<cname> param1 </cname>
				<reverse> bool </reverse>
				<default> 高攀1 </default>
				<descr> 参数注释1 </descr>
				<width> 50 </width>
			</param>
			<param>
				<dlgStyle> comcheckbox 
					<item>
						<name> 美艳1 </name>
						<value> 0 </value>
					</item>
					<item>
						<name> 美艳2 </name>
						<value> 1 </value>
					</item>
				</dlgStyle>
				<name> 参数2 </name>
				<cname> param2 </cname>
				<default> 美艳2 </default>
				<descr> 参数注释2 </descr>
				<width> 50 </width>
			</param>
			<param>
				<dlgStyle> edit </dlgStyle>
				<name> 参数3 </name>
				<cname> param3 </cname>
				<default> 王芬 </default>
				<descr> 参数注释3 </descr>
				<width> 50 </width>
			</param>
		</item>
		<item>
			<dlgStyle> static </dlgStyle>
			<name> -------------------gaopan-------------------- </name>
			<width> 1200 </width>
		</item>
		<item>
			<dlgStyle> radio </dlgStyle>
			<name> 测试2 </name>
			<value> 1 </value>
			<nonewline> 1 </nonewline>
			<param>
				<dlgStyle> edit </dlgStyle>
				<name> 参数1 </name>
				<cname> param1 </cname>
				<default> 王芬 </default>
				<descr> 参数注释1 </descr>
				<width> 50 </width>
			</param>
		</item>
		<item>
			<dlgStyle> radio </dlgStyle>
			<name> 测试3 </name>
			<value> 2 </value>
		</item>
	</testCheck>
</root>